aurigma/asset_generator/__init__.py
aurigma/asset_generator/api_client.py
aurigma/asset_generator/api_response.py
aurigma/asset_generator/configuration.py
aurigma/asset_generator/exceptions.py
aurigma/asset_generator/py.typed
aurigma/asset_generator/rest.py
aurigma/asset_generator/api/__init__.py
aurigma/asset_generator/api/build_info_api.py
aurigma/asset_generator/api/mockup_generator_api.py
aurigma/asset_generator/api/tenants_api.py
aurigma/asset_generator/models/__init__.py
aurigma/asset_generator/models/bad_request_dto.py
aurigma/asset_generator/models/build_info_model.py
aurigma/asset_generator/models/conflict_dto.py
aurigma/asset_generator/models/mockup_creation_model.py
aurigma/asset_generator/models/mockup_generation_result.py
aurigma/asset_generator/models/mockup_spec_dto.py
aurigma/asset_generator/models/mockup_spec_param_dto.py
aurigma/asset_generator/models/mockup_spec_param_rules_dto.py
aurigma/asset_generator/models/mockup_spec_params_validation_result_dto.py
aurigma/asset_generator/models/problem_details.py
aurigma/asset_generator/models/spec_group_type.py
aurigma/asset_generator/models/tenant_creation_model.py
aurigma/asset_generator/models/tenant_dto.py
aurigma/asset_generator/models/tenant_update_model.py
aurigma_asset_generator_api_client-1.0.0.dist-info/METADATA
aurigma_asset_generator_api_client-1.0.0.dist-info/WHEEL
aurigma_asset_generator_api_client-1.0.0.dist-info/top_level.txt
aurigma_asset_generator_api_client-1.0.0.dist-info/RECORD
